setup.py
shinkenplugins/__init__.py
shinkenplugins.plugins.stm_metro_montreal.egg-info/PKG-INFO
shinkenplugins.plugins.stm_metro_montreal.egg-info/SOURCES.txt
shinkenplugins.plugins.stm_metro_montreal.egg-info/dependency_links.txt
shinkenplugins.plugins.stm_metro_montreal.egg-info/entry_points.txt
shinkenplugins.plugins.stm_metro_montreal.egg-info/namespace_packages.txt
shinkenplugins.plugins.stm_metro_montreal.egg-info/requires.txt
shinkenplugins.plugins.stm_metro_montreal.egg-info/top_level.txt
shinkenplugins/plugins/__init__.py
shinkenplugins/plugins/stm_metro_montreal/__init__.py
shinkenplugins/plugins/stm_metro_montreal/stm_metro_montreal.py
shinkenplugins/plugins/stm_metro_montreal/version.py