Metadata-Version: 1.0
Name: shinkenplugins.plugins.stm-metro-montreal
Version: 0.2
Summary: Check STM Metro Montreal
Home-page: https://github.com/savoirfairelinux/monitoring-tools
Author: Grégory Starck
Author-email: gregory.starck@savoirfairelinux.com
License: GPL3+
Platform: any
